Clique_blockchain-0.2.3.dist-info/DESCRIPTION.rst
Clique_blockchain-0.2.3.dist-info/LICENSE.txt
Clique_blockchain-0.2.3.dist-info/METADATA
Clique_blockchain-0.2.3.dist-info/RECORD
Clique_blockchain-0.2.3.dist-info/WHEEL
Clique_blockchain-0.2.3.dist-info/entry_points.txt
Clique_blockchain-0.2.3.dist-info/metadata.json
Clique_blockchain-0.2.3.dist-info/top_level.txt
clique/__about__.py
clique/__init__.py
clique/authchain.py
clique/blockchain.py
clique/chainstore.py
clique/common.py
clique/identitychain.py
clique/keystore.py
clique/app/__init__.py
clique/app/__main__.py
clique/app/_authchain_example.py
clique/app/_contract_example.py
clique/app/_manufacture_example.py
clique/app/blockchain.py
clique/app/examples.py
clique/app/identity.py
clique/app/keygen.py
clique/app/utils.py
