Metadata-Version: 2.0
Name: Clique-blockchain
Version: 0.2.3
Summary: Python API for Clique block chains; ID chains and auth chains included.
Home-page: https://github.com/nicfit/clique
Author: Travis Shirk
Author-email: travis@pobox.com
License: GNU LGPL v3.0
Download-URL: https://github.com/nicfit/clique/releases/downloads/v0.2.3/Clique-blockchain-0.2.3.tar.gz
Keywords: clique
Platform: Any
Classifier: Intended Audience :: Developers
Classifier: Operating System :: POSIX
Classifier: Natural Language :: English
Classifier: License :: OSI Approved :: GNU Lesser General Public License v3 (LGPLv3)
Classifier: Programming Language :: Python
Classifier: Programming Language :: Python :: 3.5
Classifier: Programming Language :: Python :: 3.6
Classifier: Development Status :: 5 - Production/Stable
Requires-Dist: cryptography
Requires-Dist: jwcrypto
Requires-Dist: nicfit.py (>=0.5.10)
Requires-Dist: requests
